pleroma.py
pleroma.py-0.0.6.dist-info/LICENSE.md
pleroma.py-0.0.6.dist-info/METADATA
pleroma.py-0.0.6.dist-info/WHEEL
pleroma.py-0.0.6.dist-info/top_level.txt
pleroma.py-0.0.6.dist-info/RECORD
