Metadata-Version: 2.1
Name: pleroma.py
Version: 0.0.6
Home-page: https://github.com/ioistired/pleroma.py
Author: io
License: AGPL-3.0-only
Classifier: Development Status :: 3 - Alpha
Classifier: Intended Audience :: Developers
Classifier: Natural Language :: English
Classifier: Operating System :: OS Independent
License-File: LICENSE.md
Requires-Dist: aiohttp ~=3.0
Requires-Dist: anyio ~=3.0
Requires-Dist: python-dateutil ~=2.8
